{
  "title": "order filter",
  "$schema": "http://json-schema.org/draft-04/schema#",
  "javaType": "com.sos.joc.model.order.OrderFilter",
  "type": "object",
  "required": [
    "jobschedulerId",
    "workflow",
    "orderId"
  ],
  "properties": {
    "jobschedulerId": {
      "$ref": "../common/filename100-schema.json"
    },
    "workflow": {
      "$ref": "../common/path-schema.json"
    },
    "orderId": {
      "$ref": "../common/string255-schema.json"
    },
    "suppressNotExistException": {
      "$ref": "../common/suppressNotExistExceptionParam-schema.json"
    }
  }
}
